orq_ai_sdk/__init__.py
orq_ai_sdk/_hooks/__init__.py
orq_ai_sdk/_hooks/globalhook.py
orq_ai_sdk/_hooks/registration.py
orq_ai_sdk/_hooks/sdkhooks.py
orq_ai_sdk/_hooks/types.py
orq_ai_sdk/_version.py
orq_ai_sdk/agents.py
orq_ai_sdk/basesdk.py
orq_ai_sdk/budgets.py
orq_ai_sdk/chunking.py
orq_ai_sdk/contacts.py
orq_ai_sdk/datasets.py
orq_ai_sdk/deployments.py
orq_ai_sdk/evals.py
orq_ai_sdk/feedback.py
orq_ai_sdk/files.py
orq_ai_sdk/httpclient.py
orq_ai_sdk/knowledge.py
orq_ai_sdk/langchain/__init__.py
orq_ai_sdk/memorystores.py
orq_ai_sdk/metrics.py
orq_ai_sdk/models/__init__.py
orq_ai_sdk/models/actionreviewedstreamingevent.py
orq_ai_sdk/models/actionreviewrequestedstreamingevent.py
orq_ai_sdk/models/agenterroredstreamingevent.py
orq_ai_sdk/models/agentexecutionstartedstreamingevent.py
orq_ai_sdk/models/agenthandedoffstreamingevent.py
orq_ai_sdk/models/agentinactivestreamingevent.py
orq_ai_sdk/models/agentmessagecreatedstreamingevent.py
orq_ai_sdk/models/agentstartedstreamingevent.py
orq_ai_sdk/models/agentthoughtstreamingevent.py
orq_ai_sdk/models/apierror.py
orq_ai_sdk/models/audiocontentpartschema.py
orq_ai_sdk/models/cleardatasetop.py
orq_ai_sdk/models/createagentrequestop.py
orq_ai_sdk/models/createagentresponserequestop.py
orq_ai_sdk/models/createbudgetop.py
orq_ai_sdk/models/createchunkop.py
orq_ai_sdk/models/createcontactop.py
orq_ai_sdk/models/createdatasetitemop.py
orq_ai_sdk/models/createdatasetop.py
orq_ai_sdk/models/createdatasourceop.py
orq_ai_sdk/models/createevalop.py
orq_ai_sdk/models/createfeedbackop.py
orq_ai_sdk/models/createknowledgeop.py
orq_ai_sdk/models/creatememorydocumentop.py
orq_ai_sdk/models/creatememoryop.py
orq_ai_sdk/models/creatememorystoreop.py
orq_ai_sdk/models/createpromptop.py
orq_ai_sdk/models/createtoolop.py
orq_ai_sdk/models/datapart.py
orq_ai_sdk/models/deleteagentop.py
orq_ai_sdk/models/deletebudgetop.py
orq_ai_sdk/models/deletechunkop.py
orq_ai_sdk/models/deletechunksop.py
orq_ai_sdk/models/deletecontactop.py
orq_ai_sdk-4.0.51.dist-info/METADATA
orq_ai_sdk-4.0.51.dist-info/WHEEL
orq_ai_sdk-4.0.51.dist-info/RECORD
