Metadata-Version: 2.4
Name: orq-ai-sdk
Version: 4.0.51
Summary: Python Client SDK for the Orq API.
Author: Orq
Requires-Python: >=3.9.2
Classifier: Programming Language :: Python :: 3
Classifier: Programming Language :: Python :: 3.10
Classifier: Programming Language :: Python :: 3.11
Classifier: Programming Language :: Python :: 3.12
Classifier: Programming Language :: Python :: 3.13
Classifier: Programming Language :: Python :: 3.14
Requires-Dist: httpcore (>=1.0.9)
Requires-Dist: httpx (>=0.28.1)
Requires-Dist: pydantic (>=2.11.2)
Requires-Dist: requests (==2.32.4)
Project-URL: Repository, https://github.com/orq-ai/orq-python.git
